routeviews/__init__.py
routeviews/api.py
routeviews/bgpsummary.py
routeviews/const.py
routeviews/defaults.py
routeviews/parse.py
routeviews/types.py
routeviews/yaml.py
routeviews/ansible/__init__.py
routeviews/ansible/parse.py
routeviews/ansible/data/__init__.py
routeviews/ansible/data/collector.py
routeviews/ansible/data/inventory.py
routeviews/ansible/data/neighbor.py
routeviews/peeringdb/__init__.py
routeviews/peeringdb/auth.py
routeviews/peeringdb/get.py
routeviews/peeringdb/parse.py
routeviews/peeringdb/repository.py
routeviews/peeringdb/data/__init__.py
routeviews/peeringdb/data/contact.py
routeviews/peeringdb/data/network.py
routeviews/peeringdb/data/peer_request.py
routeviews/peeringdb/data/router.py
routeviews/scripts/__init__.py
routeviews/scripts/ansible_peering_request.py
routeviews/scripts/format_ansible_inventory.py
routeviews/scripts/rv_get_peers_email.py
routeviews/scripts/template.py
routeviews-0.1.3.dist-info/METADATA
routeviews-0.1.3.dist-info/WHEEL
routeviews-0.1.3.dist-info/entry_points.txt
routeviews-0.1.3.dist-info/top_level.txt
routeviews-0.1.3.dist-info/RECORD
