Metadata-Version: 2.1
Name: routeviews
Version: 0.1.3
Summary: CLI tools that support RouteViews.
Home-page: https://github.com/routeviews/routeviews-cli
Author: University of Oregon
Author-email: rleonar7@uoregon.edu
License: MIT
Keywords: RouteViews,CLI,peeringdb,API,Integration
Platform: UNKNOWN
Classifier: Development Status :: 3 - Alpha
Classifier: Intended Audience :: Developers
Classifier: Topic :: System :: Networking :: Monitoring
Classifier: License :: OSI Approved :: MIT License
Classifier: Programming Language :: Python :: 3.8
Requires-Dist: ConfigArgParse (>=1)
Requires-Dist: PyYAML (>=6)
Requires-Dist: netmiko (>=3)
Requires-Dist: pathvalidate (>=2)
Requires-Dist: rdap (>=1)
Requires-Dist: requests (>=2)
Requires-Dist: ruamel.yaml (>=0.17)
Requires-Dist: tabulate (>=0.8)
Requires-Dist: uologging (>=0.7.3)
